CHANGELOG.md
LICENSE
MANIFEST.in
README.md
requirements.txt
setup.cfg
setup.py
requirements/audio.txt
requirements/detection.txt
requirements/devel.txt
requirements/docs.txt
requirements/image.txt
requirements/integrate.txt
requirements/test.txt
requirements/text.txt
tm_examples/bert_score-own_model.py
torchmetrics_sdv2/__about__.py
torchmetrics_sdv2/__init__.py
torchmetrics_sdv2/aggregation.py
torchmetrics_sdv2/collections.py
torchmetrics_sdv2/metric.py
torchmetrics_sdv2/py.typed
torchmetrics_sdv2/setup_tools.py
torchmetrics_sdv2.egg-info/PKG-INFO
torchmetrics_sdv2.egg-info/SOURCES.txt
torchmetrics_sdv2.egg-info/dependency_links.txt
torchmetrics_sdv2.egg-info/not-zip-safe
torchmetrics_sdv2.egg-info/requires.txt
torchmetrics_sdv2.egg-info/top_level.txt
torchmetrics_sdv2/audio/__init__.py
torchmetrics_sdv2/audio/pesq.py
torchmetrics_sdv2/audio/pit.py
torchmetrics_sdv2/audio/si_sdr.py
torchmetrics_sdv2/audio/si_snr.py
torchmetrics_sdv2/audio/snr.py
torchmetrics_sdv2/audio/stoi.py
torchmetrics_sdv2/classification/__init__.py
torchmetrics_sdv2/classification/accuracy.py
torchmetrics_sdv2/classification/auc.py
torchmetrics_sdv2/classification/auroc.py
torchmetrics_sdv2/classification/avg_precision.py
torchmetrics_sdv2/classification/binned_precision_recall.py
torchmetrics_sdv2/classification/calibration_error.py
torchmetrics_sdv2/classification/cohen_kappa.py
torchmetrics_sdv2/classification/confusion_matrix.py
torchmetrics_sdv2/classification/f_beta.py
torchmetrics_sdv2/classification/hamming_distance.py
torchmetrics_sdv2/classification/hinge.py
torchmetrics_sdv2/classification/iou.py
torchmetrics_sdv2/classification/kl_divergence.py
torchmetrics_sdv2/classification/matthews_corrcoef.py
torchmetrics_sdv2/classification/precision_recall.py
torchmetrics_sdv2/classification/precision_recall_curve.py
torchmetrics_sdv2/classification/roc.py
torchmetrics_sdv2/classification/specificity.py
torchmetrics_sdv2/classification/stat_scores.py
torchmetrics_sdv2/detection/__init__.py
torchmetrics_sdv2/detection/map.py
torchmetrics_sdv2/functional/__init__.py
torchmetrics_sdv2/functional/self_supervised.py
torchmetrics_sdv2/functional/audio/__init__.py
torchmetrics_sdv2/functional/audio/pesq.py
