Metadata-Version: 2.1
Name: torchmetrics-sdv2
Version: 0.6.0
Summary: PyTorch native Metrics
Home-page: https://github.com/PyTorchLightning/metrics
Download-URL: https://github.com/PyTorchLightning/metrics/archive/master.zip
Author: PyTorchLightning et al.
Author-email: name@pytorchlightning.ai
License: Apache-2.0
Project-URL: Bug Tracker, https://github.com/PyTorchLightning/metrics/issues
Project-URL: Documentation, https://torchmetrics_sdv2.rtfd.io/en/latest/
Project-URL: Source Code, https://github.com/PyTorchLightning/metrics
Keywords: deep learning,machine learning,pytorch,metrics,AI
Classifier: Environment :: Console
Classifier: Natural Language :: English
Classifier: Development Status :: 3 - Alpha
Classifier: Intended Audience :: Developers
Classifier: Topic :: Scientific/Engineering :: Artificial Intelligence
Classifier: Topic :: Scientific/Engineering :: Image Recognition
Classifier: Topic :: Scientific/Engineering :: Information Analysis
Classifier: Operating System :: OS Independent
Classifier: Programming Language :: Python :: 3
Classifier: Programming Language :: Python :: 3.6
Classifier: Programming Language :: Python :: 3.7
Classifier: Programming Language :: Python :: 3.8
Classifier: Programming Language :: Python :: 3.9
Requires-Python: >=3.6
Provides-Extra: audio
Provides-Extra: detection
Provides-Extra: docs
Provides-Extra: image
Provides-Extra: integrate
Provides-Extra: test
Provides-Extra: text
Provides-Extra: all
License-File: LICENSE
